README.txt
setup.py
M30W/COPYING.txt
M30W/IO.py
M30W/__init__.py
M30W/config.py
M30W/costume.py
M30W/debug.py
M30W/lists.py
M30W/media.py
M30W/project.py
M30W/runtime.py
M30W/scripts.py
M30W.egg-info/PKG-INFO
M30W.egg-info/SOURCES.txt
M30W.egg-info/dependency_links.txt
M30W.egg-info/requires.txt
M30W.egg-info/top_level.txt
M30W/GUI/__init__.py
M30W/GUI/dialogs.py
M30W/GUI/errorConsole.py
M30W/GUI/leftPanel.py
M30W/GUI/main.py
M30W/GUI/mainFrame.py
M30W/GUI/menu.py
M30W/GUI/preferences.py
M30W/GUI/rightPanel.py
M30W/GUI/spritePanel.py
M30W/GUI/stage.py
M30W/compiler/__init__.py
M30W/compiler/block.py
M30W/compiler/line.py
M30W/compiler/script.py
M30W/icons/M30W.ico
M30W/icons/audio_thumbnail.png
M30W/icons/center.png
M30W/icons/duplicate.png
M30W/icons/edit.png
M30W/icons/image.png
M30W/icons/m30w.png
M30W/icons/play_dark.png
M30W/icons/play_dark_16.png
M30W/icons/play_light.png
M30W/icons/play_light_16.png
M30W/icons/refresh.png
M30W/icons/script.png
M30W/icons/sound.png
M30W/icons/stop_dark.png
M30W/icons/stop_dark_16.png
M30W/icons/stop_light.png
M30W/icons/stop_light_16.png
M30W/parser/__init__.py
M30W/parser/specs.py
M30W/parser/specshandler.py
M30W/sprites/__init__.py
M30W/sprites/base.py
M30W/sprites/sprite.py
M30W/sprites/stage.py
scripts/M30W