Metadata-Version: 1.0
Name: M30W
Version: 0.2.3
Summary: GUI text-based interface to Scratch (by MIT) projects.
Home-page: http://scratch.mit.edu/forums/viewtopic.php?id=106225
Author: roijac
Author-email: roi.jacoboson1@gmail.com
License: GPL3
Platform: UNKNOWN
